main.py
gh_downloader-0.0.1.dist-info/LICENSE
gh_downloader-0.0.1.dist-info/METADATA
gh_downloader-0.0.1.dist-info/WHEEL
gh_downloader-0.0.1.dist-info/entry_points.txt
gh_downloader-0.0.1.dist-info/top_level.txt
gh_downloader-0.0.1.dist-info/RECORD
