Metadata-Version: 2.1
Name: gh-downloader
Version: 0.0.1
Summary: CLI to download repos from Github.
Home-page: https://github.com/antwxne/Github-downloader
Author: antwxne
Author-email: antoine.desruet@epitech.eu
Project-URL: Bug Tracker, https://github.com/antwxne/Github-downloader/issues
Classifier: Programming Language :: Python :: 3
Classifier: License :: OSI Approved :: MIT License
Classifier: Operating System :: OS Independent
Requires-Python: >=3.9
License-File: LICENSE
Requires-Dist: inquirer
Requires-Dist: requests
Requires-Dist: tqdm
